pushoverutil/__init__.py
pushoverutil/cli.py
pushoverutil/push.py
pushover_util-1.2.0.dist-info/LICENSE
pushover_util-1.2.0.dist-info/METADATA
pushover_util-1.2.0.dist-info/WHEEL
pushover_util-1.2.0.dist-info/top_level.txt
pushover_util-1.2.0.dist-info/RECORD
